guardian_ai/__init__.py
guardian_ai/requirements-fairness-llm.txt
guardian_ai/requirements-fairness.txt
guardian_ai/requirements-privacy.txt
guardian_ai/fairness/__init__.py
guardian_ai/fairness/bias_mitigation/__init__.py
guardian_ai/fairness/bias_mitigation/sklearn.py
guardian_ai/fairness/llm/__init__.py
guardian_ai/fairness/llm/classifier/__init__.py
guardian_ai/fairness/llm/classifier/base.py
guardian_ai/fairness/llm/classifier/llm_classifier.py
guardian_ai/fairness/llm/classifier/toxicity.py
guardian_ai/fairness/llm/dataloader/BOLD.py
guardian_ai/fairness/llm/dataloader/__init__.py
guardian_ai/fairness/llm/dataloader/holistic_bias.py
guardian_ai/fairness/llm/dataloader/utils.py
guardian_ai/fairness/llm/evaluation/__init__.py
guardian_ai/fairness/llm/evaluation/bias_evaluator.py
guardian_ai/fairness/llm/metrics/__init__.py
guardian_ai/fairness/llm/metrics/disparity_metrics.py
guardian_ai/fairness/llm/metrics/group_metrics/__init__.py
guardian_ai/fairness/llm/metrics/group_metrics/base.py
guardian_ai/fairness/llm/metrics/group_metrics/expected_maximum_negativity_scorer.py
guardian_ai/fairness/llm/metrics/group_metrics/negative_fraction_scorer.py
guardian_ai/fairness/llm/metrics/group_metrics/negative_probability_scorer.py
guardian_ai/fairness/llm/models/__init__.py
guardian_ai/fairness/llm/models/base.py
guardian_ai/fairness/llm/models/huggingface_llm.py
guardian_ai/fairness/llm/models/openai_client.py
guardian_ai/fairness/llm/models/vllm.py
guardian_ai/fairness/metrics/__init__.py
guardian_ai/fairness/metrics/core.py
guardian_ai/fairness/metrics/dataset.py
guardian_ai/fairness/metrics/model.py
guardian_ai/fairness/metrics/utils.py
guardian_ai/fairness/utils/__init__.py
guardian_ai/fairness/utils/lazy_loader.py
guardian_ai/fairness/utils/util.py
guardian_ai/privacy_estimation/__init__.py
guardian_ai/privacy_estimation/attack.py
guardian_ai/privacy_estimation/attack_runner.py
guardian_ai/privacy_estimation/attack_tuner.py
oracle_guardian_ai-1.3.0.dist-info/licenses/LICENSE.txt
oracle_guardian_ai-1.3.0.dist-info/WHEEL
oracle_guardian_ai-1.3.0.dist-info/METADATA
oracle_guardian_ai-1.3.0.dist-info/RECORD
