Metadata-Version: 2.4
Name: oracle-guardian-ai
Version: 1.3.0
Summary: Oracle Guardian AI Open Source Project
Keywords: Oracle Cloud Infrastructure,OCI,Fairness,Bias,Privacy,AI
Author: Oracle Data Science
Requires-Python: >=3.9
Classifier: Development Status :: 5 - Production/Stable
Classifier: Intended Audience :: Developers
Classifier: License :: OSI Approved :: Universal Permissive License (UPL)
Classifier: Operating System :: OS Independent
Classifier: Programming Language :: Python :: 3.9
Classifier: Programming Language :: Python :: 3.10
Classifier: Programming Language :: Python :: 3.11
License-File: LICENSE.txt
Requires-Dist: numpy
Requires-Dist: pandas
Requires-Dist: scikit-learn==1.5.0
Requires-Dist: oracle-guardian-ai[fairness, privacy, fairness-llm] ; extra == "all-optional"
Requires-Dist: aif360==0.6.1 ; extra == "fairness"
Requires-Dist: category-encoders==2.5.0 ; extra == "fairness"
Requires-Dist: optuna==3.2.0 ; extra == "fairness"
Requires-Dist: plotly==5.4.0 ; extra == "fairness"
Requires-Dist: fairlearn==0.10.0 ; extra == "fairness"
Requires-Dist: vllm ; extra == "fairness-llm"
Requires-Dist: transformers ; extra == "fairness-llm"
Requires-Dist: requests ; extra == "fairness-llm"
Requires-Dist: torch ; extra == "fairness-llm"
Requires-Dist: detoxify ; extra == "fairness-llm"
Requires-Dist: scipy==1.10.0 ; extra == "privacy"
Requires-Dist: matplotlib==3.5.3 ; extra == "privacy"
Project-URL: Documentation, https://oracle-guardian-ai.readthedocs.io/en/latest/index.html
Project-URL: Repository, https://github.com/oracle/guardian-ai
Provides-Extra: all-optional
Provides-Extra: fairness
Provides-Extra: fairness-llm
Provides-Extra: privacy
